MANIFEST.in
Readme.md
distribute_setup.py
setup.cfg
setup.py
GEMTools/.cproject
GEMTools/.project
GEMTools/Makefile
GEMTools/Makefile.mk
GEMTools/Makefile.mk.in
GEMTools/Tasks.todo
GEMTools/config.log
GEMTools/config.status
GEMTools/configure
GEMTools/configure.ac
GEMTools/.settings/language.settings.xml
GEMTools/datasets/Bowtie.Illumina.sam
GEMTools/datasets/Bowtie.PE.sam
GEMTools/datasets/Bowtie.SE.sam
GEMTools/datasets/Bowtie2.454.sam
GEMTools/datasets/MrsFast.PE.sam
GEMTools/datasets/MrsFast.SE.sam
GEMTools/datasets/SMALT.454.sam
GEMTools/datasets/SMALT.Illumina.sam
GEMTools/datasets/TMAP.454.sam
GEMTools/datasets/gem.new.PE.Illumina.Dall.map
GEMTools/datasets/gem.new.PE.map
GEMTools/datasets/gem.new.PE.scored.map
GEMTools/datasets/gem.new.SE.454.map
GEMTools/datasets/gem.new.SE.map
GEMTools/datasets/gem.new.SE.splits.map
GEMTools/datasets/gem.old.SE.map
GEMTools/datasets/gem.old.splitmaps.map
GEMTools/datasets/small_fastq.fastq
GEMTools/datasets/stampy.454.sam
GEMTools/datasets/strampy.Illuimina.sam
GEMTools/include/gem_tools.h
GEMTools/include/gt_alignment.h
GEMTools/include/gt_alignment_utils.h
GEMTools/include/gt_attributes.h
GEMTools/include/gt_buffered_input_file.h
GEMTools/include/gt_buffered_output_file.h
GEMTools/include/gt_commons.h
GEMTools/include/gt_compact_dna_string.h
GEMTools/include/gt_counters_utils.h
GEMTools/include/gt_dna_read.h
GEMTools/include/gt_dna_string.h
GEMTools/include/gt_error.h
GEMTools/include/gt_essentials.h
GEMTools/include/gt_fm.h
GEMTools/include/gt_gemIdx_loader.h
GEMTools/include/gt_generic_printer.h
GEMTools/include/gt_gtf.h
GEMTools/include/gt_hash.h
GEMTools/include/gt_ihash.h
GEMTools/include/gt_input_fasta_parser.h
GEMTools/include/gt_input_file.h
GEMTools/include/gt_input_generic_parser.h
GEMTools/include/gt_input_map_parser.h
GEMTools/include/gt_input_map_utils.h
GEMTools/include/gt_input_parser.h
GEMTools/include/gt_input_sam_parser.h
GEMTools/include/gt_json.h
GEMTools/include/gt_map.h
python/Gemtools.egg-info/PKG-INFO
python/Gemtools.egg-info/SOURCES.txt
python/Gemtools.egg-info/dependency_links.txt
python/Gemtools.egg-info/entry_points.txt
python/Gemtools.egg-info/not-zip-safe
python/Gemtools.egg-info/requires.txt
python/Gemtools.egg-info/top_level.txt
