Metadata-Version: 1.1
Name: Gemtools
Version: 1.7.1
Summary: Python support library for the GEM mapper and the gemtools library
Home-page: https://github.com/gemtools/gemtools
Author: Thasso Griebel, Santiago Marco Sola
Author-email: thasso.griebel@gmail.com
License: GNU General Public License (GPL)
Platform: lx64
Classifier: Development Status :: 4 - Beta
Classifier: Environment :: Console
Classifier: Intended Audience :: End Users/Desktop
Classifier: Intended Audience :: Developers
Classifier: License :: OSI Approved :: GNU General Public License (GPL)
Classifier: Operating System :: POSIX :: Linux
Classifier: Programming Language :: Python
Classifier: Programming Language :: C
Classifier: Topic :: Scientific/Engineering :: Bio-Informatics
